hop3_cli/__init__.py
hop3_cli/commands/__init__.py
hop3_cli/commands/arguments.py
hop3_cli/commands/destructive.py
hop3_cli/commands/flags.py
hop3_cli/commands/help.py
hop3_cli/commands/local/__init__.py
hop3_cli/commands/local/auth_cmd.py
hop3_cli/commands/local/help_text.py
hop3_cli/commands/local/init_cmd.py
hop3_cli/commands/local/login_cmd.py
hop3_cli/commands/local/settings_cmd.py
hop3_cli/commands/local/ssh_ops.py
hop3_cli/commands/local/version_cmd.py
hop3_cli/config.py
hop3_cli/exceptions.py
hop3_cli/exit_codes.py
hop3_cli/main.py
hop3_cli/rpc/__init__.py
hop3_cli/rpc/client.py
hop3_cli/rpc/responses.py
hop3_cli/rpc/tunnel.py
hop3_cli/tokens.py
hop3_cli/types.py
hop3_cli/ui/__init__.py
hop3_cli/ui/console.py
hop3_cli/ui/messages.py
hop3_cli/ui/prompts.py
hop3_cli/ui/rich_printer.py
hop3_cli-0.4.0b1.dist-info/WHEEL
hop3_cli-0.4.0b1.dist-info/entry_points.txt
hop3_cli-0.4.0b1.dist-info/METADATA
hop3_cli-0.4.0b1.dist-info/RECORD
