Metadata-Version: 2.3
Name: hop3-cli
Version: 0.4.0b1
Summary: 
Author: Stefane Fermigier
Author-email: Stefane Fermigier <sf@abilian.com>
License: MIT
Requires-Dist: toml>=0.10.2,<1.0.0
Requires-Dist: jsonrpcclient>=4.0.3,<5.0.0
Requires-Dist: requests>=2.32.3,<3.0.0
Requires-Dist: tabulate>=0.9.0,<1.0.0
Requires-Dist: rich>=13.0.0
Requires-Dist: sshtunnel>=0.4.0
Requires-Dist: paramiko>=2.11.0,<3.0.0
Requires-Dist: loguru>=0.7.3
Requires-Dist: pathspec>=0.12.1
Requires-Dist: platformdirs>=4.3.8
Requires-Python: >=3.10, <4.0
